video2audio/__init__.py
video2audio/cli.py
video2audio-2023.1.14.dist-info/METADATA
video2audio-2023.1.14.dist-info/WHEEL
video2audio-2023.1.14.dist-info/entry_points.txt
video2audio-2023.1.14.dist-info/licenses/LICENSE
video2audio-2023.1.14.dist-info/licenses/LICENSE~
video2audio-2023.1.14.dist-info/RECORD
