Metadata-Version: 2.1
Name: video2audio
Version: 2023.1.14
Summary: Extract audio tracks from A/V files using ffmpeg.
Project-URL: Homepage, https://github.com/atpage/video2audio
Project-URL: Bug Tracker, https://github.com/atpage/video2audio/issues
Author-email: Alex Page <a.t.page@gmail.com>
License: MIT License
License-File: LICENSE
License-File: LICENSE~
Classifier: License :: OSI Approved :: MIT License
Classifier: Operating System :: OS Independent
Classifier: Programming Language :: Python :: 3
Requires-Python: >=3.6
